kognic/openlabel/__init__.py
kognic/openlabel/_version.py
kognic/openlabel/models/__init__.py
kognic/openlabel/models/models.py
kognic/openlabel/models/utils/__init__.py
kognic/openlabel/models/utils/data_type_parsing.py
kognic/openlabel/schemas/__init__.py
kognic/openlabel/schemas/openlabel-1-0-0-edited.json
kognic/openlabel/schemas/openlabel-1-0-0.json
kognic/openlabel/tools/__init__.py
kognic/openlabel/tools/model_generation.py
kognic_openlabel-2.0.5.dist-info/METADATA
kognic_openlabel-2.0.5.dist-info/WHEEL
kognic_openlabel-2.0.5.dist-info/top_level.txt
kognic_openlabel-2.0.5.dist-info/RECORD
