Metadata-Version: 2.2
Name: kognic-openlabel
Version: 2.0.5
Summary: Kognic OpenLABEL Datamodel
Author-email: Kognic <new-annotation@kognic.com>
License: MIT
Project-URL: homepage, https://github.com/annotell/kognic-openlabel-python
Keywords: Kognic,OpenLABEL
Classifier: Development Status :: 5 - Production/Stable
Classifier: License :: OSI Approved :: MIT License
Classifier: Intended Audience :: Developers
Classifier: Programming Language :: Python :: 3
Requires-Python: >=3.7
Requires-Dist: pydantic<3,>2
